celery_yandex_serverless/__init__.py
celery_yandex_serverless/django.py
celery_yandex_serverless-0.1.4.dist-info/WHEEL
celery_yandex_serverless-0.1.4.dist-info/METADATA
celery_yandex_serverless-0.1.4.dist-info/RECORD
