Metadata-Version: 2.1
Name: celery-yandex-serverless
Version: 0.1.4
Summary: Package for starting Celery worker inside Yandex Cloud Serverless Container
Author: atnartur
Author-email: i@atnartur.dev
Requires-Python: >=3.8,<4.0
Classifier: Programming Language :: Python :: 3
Classifier: Programming Language :: Python :: 3.8
Classifier: Programming Language :: Python :: 3.9
Classifier: Programming Language :: Python :: 3.10
Classifier: Programming Language :: Python :: 3.11
Requires-Dist: boto3 (>=1.26.101,<2.0.0)
Requires-Dist: celery (>=5.0,<6.0)
Requires-Dist: django
Requires-Dist: pycurl (>=7.45.2,<8.0.0)
